LICENSE
MANIFEST.in
README.md
setup.py
docs/CONTRIBUTING.md
docs/index.rst
docs/pendant.aws.batch.rst
docs/pendant.aws.exception.rst
docs/pendant.aws.logs.rst
docs/pendant.aws.response.rst
docs/pendant.aws.rst
docs/pendant.aws.s3.rst
docs/pendant.rst
docs/pendant.util.rst
pendant/__init__.py
pendant/util.py
pendant.egg-info/PKG-INFO
pendant.egg-info/SOURCES.txt
pendant.egg-info/dependency_links.txt
pendant.egg-info/not-zip-safe
pendant.egg-info/requires.txt
pendant.egg-info/top_level.txt
pendant/aws/__init__.py
pendant/aws/batch.py
pendant/aws/exception.py
pendant/aws/logs.py
pendant/aws/response.py
pendant/aws/s3.py